omegasensor/__init__.py
omegasensor/bus.py
omegasensor/bus_i2c.py
omegasensor/bus_modbus.py
omegasensor/interface.py
omegasensor/interrupt.py
omegasensor/registers.py
omegasensor/smartsensor.py
omegasensor-0.5.dist-info/LICENSE
omegasensor-0.5.dist-info/METADATA
omegasensor-0.5.dist-info/WHEEL
omegasensor-0.5.dist-info/top_level.txt
omegasensor-0.5.dist-info/RECORD
