Metadata-Version: 2.1
Name: omegasensor
Version: 0.5
Summary: Omega Smartsensor Python SDK
Home-page: https://github.com/bdinhomega/omega-smartsensor-python
Author: Binh Dinh
Author-email: bdinh@omega.com
License: UNKNOWN
Platform: UNKNOWN
Classifier: Programming Language :: Python :: 3
Classifier: License :: OSI Approved :: MIT License
Classifier: Operating System :: OS Independent
Requires-Dist: MinimalModbus
Requires-Dist: bitstruct
